examples/__init__.py
examples/hello_world.py
examples/psycopg2_connect.py
examples/server_utilisation.py
examples/sqlalchemy_orm.py
examples/sqlalchemy_raw.py
qdb_superset/__init__.py
qdb_superset/db_engine_specs/__init__.py
qdb_superset/db_engine_specs/questdb.py
questdb_connect/__init__.py
questdb_connect/common.py
questdb_connect/compilers.py
questdb_connect/dialect.py
questdb_connect/identifier_preparer.py
questdb_connect/inspector.py
questdb_connect/keywords_functions.py
questdb_connect/table_engine.py
questdb_connect/types.py
questdb_connect-1.1.4.dist-info/LICENSE
questdb_connect-1.1.4.dist-info/METADATA
questdb_connect-1.1.4.dist-info/WHEEL
questdb_connect-1.1.4.dist-info/entry_points.txt
questdb_connect-1.1.4.dist-info/top_level.txt
questdb_connect-1.1.4.dist-info/RECORD
