Metadata-Version: 2.2
Name: questdb-connect
Version: 1.1.4
Summary: SqlAlchemy library
Author-email: "questdb.io" <support@questdb.io>
Project-URL: Homepage, https://github.com/questdb/questdb-connect/
Project-URL: Bug Tracker, https://github.com/questdb/questdb-connect/issues/
Project-URL: QuestDB GitHub, https://github.com/questdb/questdb/
Project-URL: QuestDB Docs, https://questdb.io/docs/
Classifier: Intended Audience :: Developers
Classifier: Topic :: Database
Classifier: License :: OSI Approved :: Apache Software License
Classifier: Programming Language :: Python :: 3.9
Classifier: Programming Language :: Python :: 3.10
Classifier: Programming Language :: Python :: 3.11
Requires-Python: >=3.9
License-File: LICENSE
Provides-Extra: test
Requires-Dist: psycopg2-binary~=2.9.6; extra == "test"
Requires-Dist: SQLAlchemy<2,>=1.4; extra == "test"
Requires-Dist: apache-superset>=3.0.0; extra == "test"
Requires-Dist: sqlparse==0.4.4; extra == "test"
Requires-Dist: pytest~=7.3.0; extra == "test"
Requires-Dist: pytest_mock~=3.11.1; extra == "test"
Requires-Dist: black~=23.3.0; extra == "test"
Requires-Dist: ruff~=0.0.269; extra == "test"
